sag_py_cache_decorator/__init__.py
sag_py_cache_decorator/lru_cache.py
sag_py_cache_decorator/py.typed
sag_py_cache_decorator/cache/__init__.py
sag_py_cache_decorator/cache/key.py
sag_py_cache_decorator/cache/lru.py
sag_py_cache_decorator-0.3.2.dist-info/licenses/LICENSE.txt
sag_py_cache_decorator-0.3.2.dist-info/METADATA
sag_py_cache_decorator-0.3.2.dist-info/WHEEL
sag_py_cache_decorator-0.3.2.dist-info/top_level.txt
sag_py_cache_decorator-0.3.2.dist-info/RECORD
